OTAnalytics/__init__.py
OTAnalytics/__main__.py
OTAnalytics/version.py
OTAnalytics/adapter_intersect/__init__.py
OTAnalytics/adapter_ui/__init__.py
OTAnalytics/adapter_ui/abstract_button_quick_save_config.py
OTAnalytics/adapter_ui/abstract_canvas.py
OTAnalytics/adapter_ui/abstract_frame.py
OTAnalytics/adapter_ui/abstract_frame_canvas.py
OTAnalytics/adapter_ui/abstract_frame_filter.py
OTAnalytics/adapter_ui/abstract_frame_offset.py
OTAnalytics/adapter_ui/abstract_frame_project.py
OTAnalytics/adapter_ui/abstract_frame_remark.py
OTAnalytics/adapter_ui/abstract_frame_track_plotting.py
OTAnalytics/adapter_ui/abstract_frame_track_statistics.py
OTAnalytics/adapter_ui/abstract_main_window.py
OTAnalytics/adapter_ui/abstract_progressbar_popup.py
OTAnalytics/adapter_ui/abstract_treeview_interface.py
OTAnalytics/adapter_ui/cancel_export_counts.py
OTAnalytics/adapter_ui/cancel_export_file.py
OTAnalytics/adapter_ui/default_values.py
OTAnalytics/adapter_ui/dto.py
OTAnalytics/adapter_ui/dummy_viewmodel.py
OTAnalytics/adapter_ui/file_export_dto.py
OTAnalytics/adapter_ui/file_selection_cancelled.py
OTAnalytics/adapter_ui/flow_adapter.py
OTAnalytics/adapter_ui/flow_dto.py
OTAnalytics/adapter_ui/helpers.py
OTAnalytics/adapter_ui/info_box.py
OTAnalytics/adapter_ui/message_box.py
OTAnalytics/adapter_ui/text_resources.py
OTAnalytics/adapter_ui/ui_factory.py
OTAnalytics/adapter_ui/ui_texts.py
OTAnalytics/adapter_ui/view_model.py
OTAnalytics/adapter_visualization/__init__.py
OTAnalytics/adapter_visualization/color_provider.py
OTAnalytics/application/__init__.py
OTAnalytics/application/application.py
OTAnalytics/application/config.py
OTAnalytics/application/config_specification.py
OTAnalytics/application/datastore.py
OTAnalytics/application/eventlist.py
OTAnalytics/application/exception.py
OTAnalytics/application/geometry.py
OTAnalytics/application/logger.py
OTAnalytics/application/playback.py
OTAnalytics/application/plotting.py
OTAnalytics/application/progress.py
otanalytics-0.7.2.dist-info/METADATA
otanalytics-0.7.2.dist-info/WHEEL
otanalytics-0.7.2.dist-info/licenses/LICENSE
otanalytics-0.7.2.dist-info/RECORD
